mcp_code_snippets/__init__.py
mcp_code_snippets/config.py
mcp_code_snippets/main.py
mcp_code_snippets/proxy.py
mcp_code_snippets/settings.py
mcp_code_snippets/utils.py
mcp_code_snippets/cli/__init__.py
mcp_code_snippets/cli/cli.py
mcp_code_snippets/explore/__init__.py
mcp_code_snippets/explore/detect_language.py
mcp_code_snippets/explore/extract_deps/__init__.py
mcp_code_snippets/explore/extract_deps/base.py
mcp_code_snippets/explore/extract_deps/csharp.py
mcp_code_snippets/explore/extract_deps/golang.py
mcp_code_snippets/explore/extract_deps/java.py
mcp_code_snippets/explore/extract_deps/python.py
mcp_code_snippets/explore/extract_deps/rust.py
mcp_code_snippets/explore/extract_deps/typescript.py
mcp_code_snippets-0.1.2.dist-info/METADATA
mcp_code_snippets-0.1.2.dist-info/WHEEL
mcp_code_snippets-0.1.2.dist-info/entry_points.txt
mcp_code_snippets-0.1.2.dist-info/RECORD
