Metadata-Version: 2.4
Name: mcp-code-snippets
Version: 0.1.2
Summary: Intermediate MCP server for code snippets search
Author-email: Qdrant Team <info@qdrant.tech>
License-Expression: Apache-2.0
Requires-Python: >=3.10
Requires-Dist: fastmcp<2.7.0
Requires-Dist: pydantic<2.12.0
Requires-Dist: tomli>=2.0; python_full_version < '3.11'
